Metadata-Version: 2.1
Name: a-pandas-ex-adb-activities2df
Version: 0.10
Summary: Converts AndroidManifest.xml into a Pandas DataFrame (with all activities, queries, permissions ...)
Home-page: https://github.com/hansalemaos/a_pandas_ex_adb_activities2df
Author: Johannes Fischer
Author-email: <aulasparticularesdealemaosp@gmail.com>
License: MIT
Keywords: adb,android,debugging,pandas,DataFrame,AndroidManifest
Classifier: Development Status :: 4 - Beta
Classifier: Programming Language :: Python :: 3 :: Only
Classifier: Programming Language :: Python :: 3.9
Classifier: Topic :: Scientific/Engineering :: Visualization
Classifier: Topic :: Software Development :: Libraries :: Python Modules
Classifier: Topic :: Text Editors :: Text Processing
Classifier: Topic :: Text Processing :: General
Classifier: Topic :: Text Processing :: Indexing
Classifier: Topic :: Text Processing :: Filters
Classifier: Topic :: Utilities
License-File: LICENSE.rst
Requires-Dist: a-pandas-ex-plode-tool
Requires-Dist: a-pandas-ex-xml2df
Requires-Dist: flatten-everything
Requires-Dist: pandas
Requires-Dist: regex
Requires-Dist: subprocess-print-and-capture
